Metadata-Version: 2.1
Name: treeart
Version: 0.0.2
Summary: Draw ASCII trees easily
Home-page: https://github.com/taliesinb/treeart
Author: Taliesin Beynon
Author-email: contact@taliesin.ai
License: MIT
Download-URL: https://github.com/taliesinb/treeart/archive/v0.0.1.tar.gz
Keywords: ascii,tree,art,binary
Platform: UNKNOWN
Classifier: License :: OSI Approved :: MIT License
Classifier: Programming Language :: Python :: 3
Classifier: Programming Language :: Python :: 3.7
